django_simple_export_admin/__init__.py
django_simple_export_admin/admin.py
django_simple_export_admin/apps.py
django_simple_export_admin/models.py
django_simple_export_admin/tests.py
django_simple_export_admin/views.py
django_simple_export_admin/locale/zh_hans/LC_MESSAGES/django.mo
django_simple_export_admin/locale/zh_hans/LC_MESSAGES/django.po
django_simple_export_admin/migrations/__init__.py
django_simple_export_admin-0.1.10.dist-info/LICENSE
django_simple_export_admin-0.1.10.dist-info/METADATA
django_simple_export_admin-0.1.10.dist-info/WHEEL
django_simple_export_admin-0.1.10.dist-info/top_level.txt
django_simple_export_admin-0.1.10.dist-info/RECORD
