Metadata-Version: 2.1
Name: django-simple-export-admin
Version: 0.1.10
Summary: A simple django admin allow your export queryset to xlsx file.
Author: Feng YingLiang
Author-email: fengyingliang@zencore.cn
Maintainer: Feng YingLiang
Maintainer-email: fengyingliang@zencore.cn
License: MIT
Keywords: django admin extentions,django simple export admin
Classifier: Development Status :: 5 - Production/Stable
Classifier: Intended Audience :: Developers
Classifier: Topic :: Software Development :: Libraries :: Python Modules
Classifier: License :: OSI Approved :: MIT License
Classifier: Programming Language :: Python :: 3
Classifier: Programming Language :: Python :: 3 :: Only
License-File: LICENSE
Requires-Dist: openpyxl
Requires-Dist: zenutils
Requires-Dist: xlsxhelper
Requires-Dist: django
Requires-Dist: django-static-fontawesome
Requires-Dist: django-changelist-toolbar-admin
